gardena_bluetooth/__init__.py
gardena_bluetooth/__main__.py
gardena_bluetooth/client.py
gardena_bluetooth/const.py
gardena_bluetooth/exceptions.py
gardena_bluetooth/parse.py
gardena_bluetooth/py.typed
gardena_bluetooth-1.6.0.dist-info/LICENSE.txt
gardena_bluetooth-1.6.0.dist-info/METADATA
gardena_bluetooth-1.6.0.dist-info/WHEEL
gardena_bluetooth-1.6.0.dist-info/RECORD
