Metadata-Version: 2.3
Name: gardena-bluetooth
Version: 1.6.0
Summary: 
License: MIT
Author: Joakim Plate
Author-email: elupus@ecce.se
Requires-Python: >=3.10,<4.0
Classifier: License :: OSI Approved :: MIT License
Classifier: Programming Language :: Python :: 3
Classifier: Programming Language :: Python :: 3.10
Classifier: Programming Language :: Python :: 3.11
Classifier: Programming Language :: Python :: 3.12
Classifier: Programming Language :: Python :: 3.13
Provides-Extra: cli
Provides-Extra: test
Requires-Dist: asyncclick (>=8.1.3.4,<9.0.0.0) ; extra == "cli" or extra == "test"
Requires-Dist: black (>=23.3.0,<24.0.0) ; extra == "test"
Requires-Dist: bleak (>=0.20.2)
Requires-Dist: bleak-retry-connector (>=3.0.2)
Requires-Dist: pytest-asyncio (>=0.21.0,<0.22.0) ; extra == "test"
Requires-Dist: ruff (>=0.0.272,<0.0.273) ; extra == "test"
Requires-Dist: tzlocal (>=5.0.1,<6.0.0)
